{
  "main": {
    "id": "f737509cb6082729",
    "type": "split",
    "children": [
      {
        "id": "b60038f98cd8a21d",
        "type": "tabs",
        "children": [
          {
            "id": "659fa82adb6de0d4",
            "type": "leaf",
            "state": {
              "type": "markdown",
              "state": {
                "file": "作业_项目/在线教育.md",
                "mode": "source",
                "backlinks": true,
                "source": false
              }
            }
          }
        ]
      }
    ],
    "direction": "vertical"
  },
  "left": {
    "id": "e52d9e8b1b6f3e00",
    "type": "split",
    "children": [
      {
        "id": "e36a56a2c22c4d7f",
        "type": "tabs",
        "children": [
          {
            "id": "dffa4a99190b03d1",
            "type": "leaf",
            "state": {
              "type": "file-explorer",
              "state": {
                "sortOrder": "alphabetical"
              }
            }
          },
          {
            "id": "c26d4079878024b2",
            "type": "leaf",
            "state": {
              "type": "search",
              "state": {
                "query": "",
                "matchingCase": true,
                "explainSearch": false,
                "collapseAll": false,
                "extraContext": false,
                "sortOrder": "alphabetical"
              }
            }
          },
          {
            "id": "46a52e3d59bfe9b4",
            "type": "leaf",
            "state": {
              "type": "starred",
              "state": {}
            }
          },
          {
            "id": "b4ddbb48c4d297b0",
            "type": "leaf",
            "state": {
              "type": "bookmarks",
              "state": {}
            }
          }
        ]
      }
    ],
    "direction": "horizontal",
    "width": 235.5
  },
  "right": {
    "id": "9f3c7f3f0e193034",
    "type": "split",
    "children": [
      {
        "id": "19418f9ce6310b8a",
        "type": "tabs",
        "children": [
          {
            "id": "fb8cec4c798bbf3c",
            "type": "leaf",
            "state": {
              "type": "backlink",
              "state": {
                "file": "作业_项目/在线教育.md",
                "collapseAll": false,
                "extraContext": false,
                "sortOrder": "alphabetical",
                "showSearch": false,
                "searchQuery": "",
                "backlinkCollapsed": false,
                "unlinkedCollapsed": true
              }
            }
          },
          {
            "id": "7d9480cc5f1c9b5c",
            "type": "leaf",
            "state": {
              "type": "outgoing-link",
              "state": {
                "file": "作业_项目/在线教育.md",
                "linksCollapsed": false,
                "unlinkedCollapsed": true
              }
            }
          },
          {
            "id": "18ce653a559ba591",
            "type": "leaf",
            "state": {
              "type": "tag",
              "state": {
                "sortOrder": "frequency",
                "useHierarchy": true
              }
            }
          },
          {
            "id": "3fc030083824475d",
            "type": "leaf",
            "state": {
              "type": "outline",
              "state": {
                "file": "作业_项目/在线教育.md"
              }
            }
          },
          {
            "id": "4222dea9a345a5b7",
            "type": "leaf",
            "state": {
              "type": "QUICKSHARE_SIDE_VIEW",
              "state": {}
            }
          },
          {
            "id": "806e1744f21f2b3c",
            "type": "leaf",
            "state": {
              "type": "advanced-tables-toolbar",
              "state": {}
            }
          }
        ],
        "currentTab": 5
      }
    ],
    "direction": "horizontal",
    "width": 200,
    "collapsed": true
  },
  "left-ribbon": {
    "hiddenItems": {
      "canvas:新建白板": false,
      "switcher:打开快速切换": false,
      "graph:查看关系图谱": false,
      "daily-notes:打开/创建今天的日记": false,
      "templates:插入模板": false,
      "command-palette:打开命令面板": false,
      "obsidian-excalidraw-plugin:新建 Excalidraw 绘图": false,
      "table-editor-obsidian:Advanced Tables Toolbar": false
    }
  },
  "active": "659fa82adb6de0d4",
  "lastOpenFiles": [
    "课上 copy.ipynb",
    "导入 切分数据集 的函数.md",
    "作业_项目/在线教育.md",
    "超参数调整.md",
    "保存模型.md",
    "笔记/逻辑回归-项目介绍.md",
    "One-Hot编码.md",
    "对两个类别变量的相关性进行分析（类别-类别）.md",
    "特征-目标值.md",
    "sns箱型图中位数相关分析函数（连续-类别）.md",
    "类别-连续.md",
    "笔记/决策树.md",
    "笔记/stats.md",
    "导入 3d matplotlib库.md",
    "卡方.md",
    "笔记/PCA算法.md",
    "Pasted image 20230615213036.png",
    "Pasted image 20230615212554.png",
    "笔记/XGBoost.md",
    "Pasted image 20230612222131.png",
    "XGBoost和GBDT的区别.md",
    "作业_项目/情感分析（哪吒影评）.md",
    "笔记/贝叶斯.md",
    "轮廓系数.md",
    "笔记/K-Means.md",
    "肘部法则.md",
    "计算一组点与另一组点之间的最近邻索引.md",
    "KMeans++算法步骤.md",
    "条形或不规则形状的数据.md",
    "Pasted image 20230611152540.png",
    "Pasted image 20230611151723.png",
    "Pasted image 20230611151610.png",
    "Pasted image 20230611150150.png",
    "Pasted image 20230610194844.png",
    "Pasted image 20230610194328.png",
    "3655049802117b044ce3a58d84e6a9e.png",
    "未命名.canvas",
    "stopword.txt",
    "comment.csv",
    "作业_项目/sms spam.csv",
    "sms spam.csv",
    "作业_项目",
    " - 副本.gitattributes",
    "笔记 - 副本",
    "obsidian - 副本",
    "Excalidraw - 副本",
    "obsidian"
  ]
}